mado/__init__.py
mado/application_window.py
mado/capabilities.py
mado/checkers.py
mado/data_repository.py
mado/db.py
mado/form_body.py
mado/input_base.py
mado/menu_screen.py
mado/report.py
mado/screen.py
mado/utils.py
mado/entity/__init__.py
mado/entity/config.py
mado/entity/directory_explorer.py
mado/entity/entity_explorer.py
mado/entity/explorer_mixins.py
mado/entity/operations.py
mado/resources/__init__.py
mado/resources/resources.py
mado/standard_inputs/__init__.py
mado/standard_inputs/controls.py
mado/standard_inputs/dates.py
mado/standard_inputs/lists.py
mado/standard_inputs/selectables.py
mado/standard_inputs/tables.py
mado/standard_inputs/text.py
mado/widgets/__init__.py
mado/widgets/misc.py
mado/widgets/modal.py
mado/widgets/tables.py
madotsuki-1.4.dist-info/LICENSE
madotsuki-1.4.dist-info/METADATA
madotsuki-1.4.dist-info/WHEEL
madotsuki-1.4.dist-info/top_level.txt
madotsuki-1.4.dist-info/RECORD
