Metadata-Version: 2.1
Name: madotsuki
Version: 1.4
Summary: Библиотека для построения графических CRUD-интерфейсов
Author: jqmxaec
License-File: LICENSE
Requires-Dist: PyQt5
Requires-Dist: SQLAlchemy
